README.md
setup.py
tests.py
tagsPlorer.egg-info/PKG-INFO
tagsPlorer.egg-info/SOURCES.txt
tagsPlorer.egg-info/dependency_links.txt
tagsPlorer.egg-info/entry_points.txt
tagsPlorer.egg-info/not-zip-safe
tagsPlorer.egg-info/top_level.txt
tagsplorer/VERSION
tagsplorer/__main__.py
tagsplorer/constants.py
tagsplorer/lib.py
tagsplorer/serve.py
tagsplorer/simfs.py
tagsplorer/supervisor.py
tagsplorer/tp.py
tagsplorer/utils.py