Metadata-Version: 2.1
Name: tagsPlorer
Version: 0.202102.71004
Summary: tagsPlorer V0.202102.71004-v0.9
Home-page: http://github.com/ArneBachmann/corrupdetect
Author: Arne Bachmann
Author-email: ArneBachmann@users.noreply.github.com
Maintainer: Arne Bachmann
Maintainer-email: ArneBachmann@users.noreply.github.com
License: MPL-2.0
Platform: UNKNOWN
Classifier: Development Status :: 5 - Production/Stable
Classifier: Intended Audience :: Other Audience
Classifier: Intended Audience :: System Administrators
Classifier: License :: OSI Approved :: Mozilla Public License 2.0 (MPL 2.0)
Classifier: Operating System :: OS Independent
Classifier: Programming Language :: Python :: 3
Classifier: Programming Language :: Python :: 3.6
Classifier: Programming Language :: Python :: 3.7
Classifier: Programming Language :: Python :: 3.8
Classifier: Programming Language :: Python :: 3.9
